extext.py
extext-0.1.dist-info/METADATA
extext-0.1.dist-info/WHEEL
extext-0.1.dist-info/top_level.txt
extext-0.1.dist-info/RECORD
